LICENSE
MANIFEST.in
README.md
requirements.txt
setup.cfg
setup.py
Quart_Kroket.egg-info/PKG-INFO
Quart_Kroket.egg-info/SOURCES.txt
Quart_Kroket.egg-info/dependency_links.txt
Quart_Kroket.egg-info/not-zip-safe
Quart_Kroket.egg-info/requires.txt
Quart_Kroket.egg-info/top_level.txt
quart_kroket/__init__.py
quart_kroket/template_filters.py
quart_kroket/utils.py
quart_kroket/data/__init__.py
quart_kroket/data/checksum.py
quart_kroket/data/structures.py
quart_kroket/database/__init__.py
quart_kroket/database/enums.py
quart_kroket/database/model.py
quart_kroket/email/__init__.py
quart_kroket/email/mjml/__init__.py
quart_kroket/email/mjml/templates/basic.jinja2
quart_kroket/finance/__init__.py
quart_kroket/finance/validation.py
quart_kroket/imaging/DejaVuSansMono.ttf
quart_kroket/imaging/__init__.py
quart_kroket/imaging/avatars.py
quart_kroket/imaging/captchav2.py
quart_kroket/imaging/imaging.py
quart_kroket/imaging/qr.py
quart_kroket/imaging/routes.py
quart_kroket/localization/__init__.py
quart_kroket/localization/countries.py
quart_kroket/markup/__init__.py
quart_kroket/markup/markdown.py
quart_kroket/media/__init__.py
quart_kroket/media/constants.py
quart_kroket/media/enums.py
quart_kroket/media/youtube.py
quart_kroket/net/__init__.py
quart_kroket/net/ftp.py
quart_kroket/net/gravatar.py
quart_kroket/net/http_agents.py
quart_kroket/net/http_requests.py
quart_kroket/oidc/__init__.py
quart_kroket/oidc/models.py
quart_kroket/pdf/__init__.py