Metadata-Version: 2.1
Name: Quart-Kroket
Version: 1.0.4
Summary: zZzZ
Home-page: https://git.kroket.io/labs/quart-kroket
Author: Kroket Ltd.
Author-email: code@kroket.io
Platform: any
Classifier: Environment :: Web Environment
Classifier: Intended Audience :: Developers
Classifier: Operating System :: OS Independent
Classifier: Programming Language :: Python :: 3
Classifier: Programming Language :: Python :: 3.7
Classifier: Programming Language :: Python :: 3.8
Classifier: License :: OSI Approved :: BSD License
Classifier: Topic :: Internet :: WWW/HTTP :: Dynamic Content
Classifier: Topic :: Software Development :: Libraries :: Python Modules
Provides-Extra: dotenv
License-File: LICENSE
